ugbio_mrd/__init__.py
ugbio_mrd/generate_mrd_report.py
ugbio_mrd/generate_synthetic_signatures.py
ugbio_mrd/mrd_utils.py
ugbio_mrd/reports/mrd_automatic_data_analysis.ipynb
ugbio_mrd-1.20.0.dist-info/METADATA
ugbio_mrd-1.20.0.dist-info/WHEEL
ugbio_mrd-1.20.0.dist-info/entry_points.txt
ugbio_mrd-1.20.0.dist-info/top_level.txt
ugbio_mrd-1.20.0.dist-info/RECORD
